{
"meta":{"test_sets":[],"test_metrics":[],"learn_metrics":[{"best_value":"Min","name":"RMSE"}],"launch_mode":"Train","parameters":"","iteration_count":100,"learn_sets":["learn"],"name":"experiment"},
"iterations":[
{"learn":[257350.6989],"iteration":0,"passed_time":0.001721694043,"remaining_time":0.1704477102},
{"learn":[157587.6566],"iteration":1,"passed_time":0.003436003885,"remaining_time":0.1683641903},
{"learn":[134809.5056],"iteration":2,"passed_time":0.004908023943,"remaining_time":0.1586927742},
{"learn":[119395.0337],"iteration":3,"passed_time":0.006403274508,"remaining_time":0.1536785882},
{"learn":[113021.0705],"iteration":4,"passed_time":0.007793256235,"remaining_time":0.1480718685},
{"learn":[107248.654],"iteration":5,"passed_time":0.009275285332,"remaining_time":0.1453128035},
{"learn":[101999.2732],"iteration":6,"passed_time":0.01082009599,"remaining_time":0.1437527039},
{"learn":[99211.46874],"iteration":7,"passed_time":0.01225875968,"remaining_time":0.1409757363},
{"learn":[92675.43502],"iteration":8,"passed_time":0.01388199192,"remaining_time":0.1403623627},
{"learn":[88380.61507],"iteration":9,"passed_time":0.01530639793,"remaining_time":0.1377575814},
{"learn":[85837.84261],"iteration":10,"passed_time":0.01674365366,"remaining_time":0.1354713796},
{"learn":[80890.53809],"iteration":11,"passed_time":0.01819878208,"remaining_time":0.1334577352},
{"learn":[77810.21063],"iteration":12,"passed_time":0.01960171384,"remaining_time":0.1311807003},
{"learn":[76854.3234],"iteration":13,"passed_time":0.02111640097,"remaining_time":0.1297150345},
{"learn":[74076.61224],"iteration":14,"passed_time":0.02257196021,"remaining_time":0.1279077745},
{"learn":[72057.77208],"iteration":15,"passed_time":0.02397719848,"remaining_time":0.125880292},
{"learn":[70602.57998],"iteration":16,"passed_time":0.02540820306,"remaining_time":0.124051815},
{"learn":[69457.21518],"iteration":17,"passed_time":0.02687008901,"remaining_time":0.1224081833},
{"learn":[68392.5509],"iteration":18,"passed_time":0.02822857355,"remaining_time":0.1203428662},
{"learn":[67918.58319],"iteration":19,"passed_time":0.02963439898,"remaining_time":0.1185375959},
{"learn":[67337.45126],"iteration":20,"passed_time":0.03108195733,"remaining_time":0.1169273633},
{"learn":[66462.67674],"iteration":21,"passed_time":0.03244675468,"remaining_time":0.1150384939},
{"learn":[66109.14496],"iteration":22,"passed_time":0.03383560031,"remaining_time":0.1132757054},
{"learn":[64418.77702],"iteration":23,"passed_time":0.03525559048,"remaining_time":0.1116427032},
{"learn":[63041.04139],"iteration":24,"passed_time":0.03663976143,"remaining_time":0.1099192843},
{"learn":[62281.92164],"iteration":25,"passed_time":0.03831546523,"remaining_time":0.1090517087},
{"learn":[61153.89567],"iteration":26,"passed_time":0.03986640066,"remaining_time":0.1077869351},
{"learn":[60679.85726],"iteration":27,"passed_time":0.04138150253,"remaining_time":0.1064095779},
{"learn":[59771.25613],"iteration":28,"passed_time":0.04297151868,"remaining_time":0.1052061319},
{"learn":[58663.54267],"iteration":29,"passed_time":0.04446059106,"remaining_time":0.1037413791},
{"learn":[58234.53709],"iteration":30,"passed_time":0.04588025985,"remaining_time":0.1021205784},
{"learn":[57834.85324],"iteration":31,"passed_time":0.04729453132,"remaining_time":0.100500879},
{"learn":[57014.11322],"iteration":32,"passed_time":0.04876228102,"remaining_time":0.09900220692},
{"learn":[56882.1839],"iteration":33,"passed_time":0.0501328935,"remaining_time":0.09731679326},
{"learn":[56075.93659],"iteration":34,"passed_time":0.05179061082,"remaining_time":0.09618256295},
{"learn":[55568.47265],"iteration":35,"passed_time":0.05319635286,"remaining_time":0.09457129397},
{"learn":[54723.86029],"iteration":36,"passed_time":0.05462881752,"remaining_time":0.09301663524},
{"learn":[54497.47366],"iteration":37,"passed_time":0.05599645252,"remaining_time":0.09136263306},
{"learn":[54163.26288],"iteration":38,"passed_time":0.05740376755,"remaining_time":0.08978538002},
{"learn":[53913.28821],"iteration":39,"passed_time":0.05880604658,"remaining_time":0.08820906988},
{"learn":[53490.05138],"iteration":40,"passed_time":0.06020524304,"remaining_time":0.08663681315},
{"learn":[53361.16136],"iteration":41,"passed_time":0.06152407968,"remaining_time":0.08496182432},
{"learn":[53330.83748],"iteration":42,"passed_time":0.06280740719,"remaining_time":0.08325633047},
{"learn":[52952.68844],"iteration":43,"passed_time":0.06432968481,"remaining_time":0.08187414431},
{"learn":[52778.55484],"iteration":44,"passed_time":0.06576573539,"remaining_time":0.08038034326},
{"learn":[52667.50974],"iteration":45,"passed_time":0.06717475805,"remaining_time":0.07885732466},
{"learn":[52647.71873],"iteration":46,"passed_time":0.06851603523,"remaining_time":0.07726276313},
{"learn":[52413.84866],"iteration":47,"passed_time":0.06995833217,"remaining_time":0.07578819319},
{"learn":[51984.39513],"iteration":48,"passed_time":0.07147110887,"remaining_time":0.07438829699},
{"learn":[51721.76546],"iteration":49,"passed_time":0.07294630835,"remaining_time":0.07294630835},
{"learn":[51533.7171],"iteration":50,"passed_time":0.07449110728,"remaining_time":0.07156988739},
{"learn":[51039.04987],"iteration":51,"passed_time":0.07608110823,"remaining_time":0.07022871529},
{"learn":[50800.57789],"iteration":52,"passed_time":0.07773416216,"remaining_time":0.06893406833},
{"learn":[50729.35659],"iteration":53,"passed_time":0.07938853851,"remaining_time":0.06762727354},
{"learn":[50413.77605],"iteration":54,"passed_time":0.08100994369,"remaining_time":0.06628086302},
{"learn":[49931.80538],"iteration":55,"passed_time":0.08263242244,"remaining_time":0.06492547477},
{"learn":[49616.77544],"iteration":56,"passed_time":0.08424693113,"remaining_time":0.06355470243},
{"learn":[49261.55907],"iteration":57,"passed_time":0.08575451027,"remaining_time":0.06209809364},
{"learn":[49042.7015],"iteration":58,"passed_time":0.08722906874,"remaining_time":0.06061681048},
{"learn":[48739.45253],"iteration":59,"passed_time":0.08865243941,"remaining_time":0.05910162627},
{"learn":[48580.55273],"iteration":60,"passed_time":0.09007669863,"remaining_time":0.05759002044},
{"learn":[48456.77644],"iteration":61,"passed_time":0.09148861712,"remaining_time":0.05607366856},
{"learn":[48368.07423],"iteration":62,"passed_time":0.09298227558,"remaining_time":0.05460863804},
{"learn":[48233.47927],"iteration":63,"passed_time":0.09446821935,"remaining_time":0.05313837339},
{"learn":[48188.04556],"iteration":64,"passed_time":0.09592745267,"remaining_time":0.05165324374},
{"learn":[48181.63304],"iteration":65,"passed_time":0.09728497049,"remaining_time":0.05011649995},
{"learn":[47929.63106],"iteration":66,"passed_time":0.09868236986,"remaining_time":0.04860474933},
{"learn":[47871.79059],"iteration":67,"passed_time":0.1003646114,"remaining_time":0.04723040538},
{"learn":[47764.43134],"iteration":68,"passed_time":0.1020103793,"remaining_time":0.04583075013},
{"learn":[47507.83416],"iteration":69,"passed_time":0.1035657271,"remaining_time":0.04438531162},
{"learn":[47385.03145],"iteration":70,"passed_time":0.1051108148,"remaining_time":0.04293258634},
{"learn":[47250.95023],"iteration":71,"passed_time":0.1066958336,"remaining_time":0.04149282419},
{"learn":[47159.10515],"iteration":72,"passed_time":0.1081981839,"remaining_time":0.04001850639},
{"learn":[47043.86055],"iteration":73,"passed_time":0.1097974039,"remaining_time":0.03857746625},
{"learn":[46979.92106],"iteration":74,"passed_time":0.1114096635,"remaining_time":0.03713655449},
{"learn":[46711.51331],"iteration":75,"passed_time":0.1130664101,"remaining_time":0.03570518215},
{"learn":[46416.89565],"iteration":76,"passed_time":0.1148235417,"remaining_time":0.03429794102},
{"learn":[46149.22861],"iteration":77,"passed_time":0.1164641923,"remaining_time":0.03284887476},
{"learn":[46093.98266],"iteration":78,"passed_time":0.1180048903,"remaining_time":0.03136838856},
{"learn":[45744.902],"iteration":79,"passed_time":0.1196968525,"remaining_time":0.02992421313},
{"learn":[45571.96035],"iteration":80,"passed_time":0.1213431733,"remaining_time":0.02846321348},
{"learn":[45567.25163],"iteration":81,"passed_time":0.1228222444,"remaining_time":0.02696098048},
{"learn":[45357.58868],"iteration":82,"passed_time":0.1244000644,"remaining_time":0.02547953127},
{"learn":[45216.14188],"iteration":83,"passed_time":0.1259107731,"remaining_time":0.02398300439},
{"learn":[45137.73591],"iteration":84,"passed_time":0.1273050534,"remaining_time":0.02246559765},
{"learn":[44962.11062],"iteration":85,"passed_time":0.1287525105,"remaining_time":0.02095971102},
{"learn":[44843.28613],"iteration":86,"passed_time":0.1302157593,"remaining_time":0.01945752725},
{"learn":[44736.3177],"iteration":87,"passed_time":0.1316934255,"remaining_time":0.01795819439},
{"learn":[44610.80408],"iteration":88,"passed_time":0.1331647086,"remaining_time":0.01645855949},
{"learn":[44556.52747],"iteration":89,"passed_time":0.1346255383,"remaining_time":0.01495839315},
{"learn":[44509.88868],"iteration":90,"passed_time":0.1360125217,"remaining_time":0.01345178786},
{"learn":[44465.2088],"iteration":91,"passed_time":0.1376130034,"remaining_time":0.01196634812},
{"learn":[44416.41199],"iteration":92,"passed_time":0.1392925832,"remaining_time":0.01048438798},
{"learn":[44359.59373],"iteration":93,"passed_time":0.1409448163,"remaining_time":0.008996477637},
{"learn":[44332.48939],"iteration":94,"passed_time":0.1423948692,"remaining_time":0.0074944668},
{"learn":[44235.14569],"iteration":95,"passed_time":0.1439069094,"remaining_time":0.005996121223},
{"learn":[44170.26775],"iteration":96,"passed_time":0.1453642153,"remaining_time":0.004495800473},
{"learn":[44132.26582],"iteration":97,"passed_time":0.1467764621,"remaining_time":0.002995438002},
{"learn":[44072.54924],"iteration":98,"passed_time":0.1482321951,"remaining_time":0.0014972949},
{"learn":[44051.64002],"iteration":99,"passed_time":0.1496884561,"remaining_time":0}
]}